turbofind-0.1.0.dist-info/METADATA
turbofind-0.1.0.dist-info/WHEEL
turbofind/__init__.py
turbofind/turbofind.cp312-win_amd64.pyd
turbofind-0.1.0.dist-info/RECORD
