Metadata-Version: 2.4
Name: turbofind
Version: 0.1.0
Classifier: Programming Language :: Rust
Classifier: Programming Language :: Python :: 3
Summary: A blazing-fast, intelligent file and directory search tool powered by Rust.
License: Proprietary
Requires-Python: >=3.8
